<?xml version="1.0" encoding="ISO-8859-1"?>
<model version="2.1">
  <id>3a7156f7-51f3-4385-8801-1fa6dfdd09a8</id>
  <name>&lt;New&gt;</name>
  <changecounter>4</changecounter>
  <sib>
    <id>542e4335-5432-4186-8a73-185342ead59a</id>
    <name>ExtractPattern</name>
    <label>ExtractPattern</label>
    <sib-uid>basic-sibs/ExtractPattern</sib-uid>
    <taxonomy>de.jabc.sib.common.basic.ExtractPattern</taxonomy>
    <position>496.0,273.0</position>
    <parameter name="group">
      <de.metaframe.common.sib.parameter.ContextExpression>
        <ContextExpressionFoundation>
          <expression>${0}</expression>
          <clazz>java.lang.Integer</clazz>
          <classMutable>false</classMutable>
        </ContextExpressionFoundation>
      </de.metaframe.common.sib.parameter.ContextExpression>
    </parameter>
    <parameter name="matches">
      <de.metaframe.jabc.framework.sib.parameter.ContextKey>
        <ContextKeyFoundation>
          <key>matches1</key>
          <scope>LOCAL</scope>
          <scopeMutable>true</scopeMutable>
        </ContextKeyFoundation>
      </de.metaframe.jabc.framework.sib.parameter.ContextKey>
    </parameter>
    <parameter name="pattern">
      <de.metaframe.common.sib.parameter.ContextExpression>
        <ContextExpressionFoundation>
          <expression>^EMap&lt;</expression>
          <clazz>java.lang.String</clazz>
          <classMutable>false</classMutable>
        </ContextExpressionFoundation>
      </de.metaframe.common.sib.parameter.ContextExpression>
    </parameter>
    <parameter name="string">
      <de.metaframe.common.sib.parameter.ContextExpression>
        <ContextExpressionFoundation>
          <expression>${string}</expression>
          <clazz>java.lang.String</clazz>
          <classMutable>false</classMutable>
        </ContextExpressionFoundation>
      </de.metaframe.common.sib.parameter.ContextExpression>
    </parameter>
    <finalbranches>default</finalbranches>
    <finalbranches>error</finalbranches>
  </sib>
  <sib>
    <id>15ce6108-b6a5-41d8-8ec3-75324b08890e</id>
    <name>PutString</name>
    <label>PutString</label>
    <sib-uid>basic-sibs/PutString</sib-uid>
    <taxonomy>de.jabc.sib.common.basic.PutString</taxonomy>
    <position>510.0,168.0</position>
    <parameter name="value">
      <string>EMap&lt;String,String&gt;</string>
    </parameter>
    <parameter name="variable">
      <de.metaframe.jabc.framework.sib.parameter.ContextKey>
        <ContextKeyFoundation>
          <key>string</key>
          <scope>LOCAL</scope>
          <scopeMutable>true</scopeMutable>
        </ContextKeyFoundation>
      </de.metaframe.jabc.framework.sib.parameter.ContextKey>
    </parameter>
    <finalbranches>default</finalbranches>
    <finalbranches>error</finalbranches>
    <userobject key="ABC$START">
      <boolean>true</boolean>
    </userobject>
  </sib>
  <sib>
    <id>12092642-3ff0-4928-88e3-8ae098c9a0c3</id>
    <name>PrintConsoleMessage</name>
    <label>PrintConsoleMessage</label>
    <sib-uid>io-sibs/PrintConsoleMessage</sib-uid>
    <taxonomy>de.jabc.sib.common.io.PrintConsoleMessage</taxonomy>
    <position>474.5,513.0</position>
    <parameter name="error">
      <boolean>false</boolean>
    </parameter>
    <parameter name="message">
      <de.metaframe.common.sib.parameter.ContextExpression>
        <ContextExpressionFoundation>
          <expression>${matches1}\n${matches2}</expression>
          <clazz>java.lang.Object</clazz>
          <classMutable>false</classMutable>
        </ContextExpressionFoundation>
      </de.metaframe.common.sib.parameter.ContextExpression>
    </parameter>
    <finalbranches>default</finalbranches>
  </sib>
  <edge>
    <source>542e4335-5432-4186-8a73-185342ead59a</source>
    <target>a9edfd89-299c-4b48-8a16-b1e06b5837db</target>
    <point>453.0,387.6857142857143</point>
    <point>522.0,407.4</point>
    <labelposition>500.0,0.0</labelposition>
    <branch>default</branch>
  </edge>
  <edge>
    <source>15ce6108-b6a5-41d8-8ec3-75324b08890e</source>
    <target>542e4335-5432-4186-8a73-185342ead59a</target>
    <point>225.0,210.0</point>
    <point>411.0,374.0</point>
    <branch>default</branch>
  </edge>
  <sib>
    <id>a9edfd89-299c-4b48-8a16-b1e06b5837db</id>
    <name>ExtractPattern_1</name>
    <label>ExtractPattern</label>
    <sib-uid>basic-sibs/ExtractPattern</sib-uid>
    <taxonomy>de.jabc.sib.common.basic.ExtractPattern</taxonomy>
    <position>496.0,393.0</position>
    <parameter name="group">
      <de.metaframe.common.sib.parameter.ContextExpression>
        <ContextExpressionFoundation>
          <expression>${0}</expression>
          <clazz>java.lang.Integer</clazz>
          <classMutable>false</classMutable>
        </ContextExpressionFoundation>
      </de.metaframe.common.sib.parameter.ContextExpression>
    </parameter>
    <parameter name="matches">
      <de.metaframe.jabc.framework.sib.parameter.ContextKey>
        <ContextKeyFoundation>
          <key>matches2</key>
          <scope>LOCAL</scope>
          <scopeMutable>true</scopeMutable>
        </ContextKeyFoundation>
      </de.metaframe.jabc.framework.sib.parameter.ContextKey>
    </parameter>
    <parameter name="pattern">
      <de.metaframe.common.sib.parameter.ContextExpression>
        <ContextExpressionFoundation>
          <expression>[[a-z][A-Z][0-9]]+</expression>
          <clazz>java.lang.String</clazz>
          <classMutable>false</classMutable>
        </ContextExpressionFoundation>
      </de.metaframe.common.sib.parameter.ContextExpression>
    </parameter>
    <parameter name="string">
      <de.metaframe.common.sib.parameter.ContextExpression>
        <ContextExpressionFoundation>
          <expression>${string}</expression>
          <clazz>java.lang.String</clazz>
          <classMutable>false</classMutable>
        </ContextExpressionFoundation>
      </de.metaframe.common.sib.parameter.ContextExpression>
    </parameter>
    <finalbranches>default</finalbranches>
    <finalbranches>error</finalbranches>
  </sib>
  <edge>
    <source>a9edfd89-299c-4b48-8a16-b1e06b5837db</source>
    <target>27c93064-43a0-44be-9daf-aa070d5a7558</target>
    <point>558.0,413.6181818181818</point>
    <point>687.0,425.3454545454546</point>
    <labelposition>500.0,0.0</labelposition>
    <branch>default</branch>
  </edge>
  <sib>
    <id>27c93064-43a0-44be-9daf-aa070d5a7558</id>
    <name>IterateElements</name>
    <label>IterateElements</label>
    <sib-uid>collection-sibs/IterateElements</sib-uid>
    <taxonomy>de.jabc.sib.common.collection.IterateElements</taxonomy>
    <position>656.0,408.0</position>
    <parameter name="collection">
      <de.metaframe.jabc.framework.sib.parameter.ContextKey>
        <ContextKeyFoundation>
          <key>matches2</key>
          <scope>LOCAL</scope>
          <scopeMutable>true</scopeMutable>
        </ContextKeyFoundation>
      </de.metaframe.jabc.framework.sib.parameter.ContextKey>
    </parameter>
    <parameter name="element">
      <de.metaframe.jabc.framework.sib.parameter.ContextKey>
        <ContextKeyFoundation>
          <key>match</key>
          <scope>LOCAL</scope>
          <scopeMutable>true</scopeMutable>
        </ContextKeyFoundation>
      </de.metaframe.jabc.framework.sib.parameter.ContextKey>
    </parameter>
    <parameter name="iterator">
      <de.metaframe.jabc.framework.sib.parameter.ContextKey>
        <ContextKeyFoundation>
          <key>iterator</key>
          <scope>LOCAL</scope>
          <scopeMutable>true</scopeMutable>
        </ContextKeyFoundation>
      </de.metaframe.jabc.framework.sib.parameter.ContextKey>
    </parameter>
    <finalbranches>error</finalbranches>
    <finalbranches>exit</finalbranches>
    <finalbranches>next</finalbranches>
  </sib>
  <edge>
    <source>27c93064-43a0-44be-9daf-aa070d5a7558</source>
    <target>8d0a4d27-21a1-4f0c-bd5e-b26d3f03c9e9</target>
    <point>706.3235294117648,444.0</point>
    <point>718.5483870967741,603.0</point>
    <branch>next</branch>
  </edge>
  <sib>
    <id>8d0a4d27-21a1-4f0c-bd5e-b26d3f03c9e9</id>
    <name>PrintConsoleMessage_1</name>
    <label>PrintConsoleMessage</label>
    <sib-uid>io-sibs/PrintConsoleMessage</sib-uid>
    <taxonomy>de.jabc.sib.common.io.PrintConsoleMessage</taxonomy>
    <position>654.5,603.0</position>
    <parameter name="error">
      <boolean>false</boolean>
    </parameter>
    <parameter name="message">
      <de.metaframe.common.sib.parameter.ContextExpression>
        <ContextExpressionFoundation>
          <expression>${match}</expression>
          <clazz>java.lang.Object</clazz>
          <classMutable>false</classMutable>
        </ContextExpressionFoundation>
      </de.metaframe.common.sib.parameter.ContextExpression>
    </parameter>
    <finalbranches>default</finalbranches>
  </sib>
  <edge>
    <source>8d0a4d27-21a1-4f0c-bd5e-b26d3f03c9e9</source>
    <target>27c93064-43a0-44be-9daf-aa070d5a7558</target>
    <point>785.5,603.0</point>
    <point>855.0,570.0</point>
    <point>754.0,462.0</point>
    <branch>default</branch>
  </edge>
  <edge>
    <source>27c93064-43a0-44be-9daf-aa070d5a7558</source>
    <target>12092642-3ff0-4928-88e3-8ae098c9a0c3</target>
    <point>705.0,435.0</point>
    <point>548.0,540.0</point>
    <branch>exit</branch>
  </edge>
  <values/>
</model>